CHANGELOG
COPYING
INSTALL
MANIFEST.in
README
THANKS
setup.cfg
setup.py
Rabbyt.egg-info/PKG-INFO
Rabbyt.egg-info/SOURCES.txt
Rabbyt.egg-info/dependency_links.txt
Rabbyt.egg-info/top_level.txt
docs/make_docs.py
docs/rabbyt/index.html
docs/rabbyt/Scheduler/index.html
docs/rabbyt/anims/index.html
docs/rabbyt/anims/Anim/index.html
docs/rabbyt/anims/AnimConst/index.html
docs/rabbyt/anims/AnimProxy/index.html
docs/rabbyt/anims/AnimPyFunc/index.html
docs/rabbyt/collisions/index.html
docs/rabbyt/primitives/index.html
docs/rabbyt/primitives/Quad/index.html
docs/rabbyt/sprites/index.html
docs/rabbyt/sprites/BaseSprite/index.html
docs/rabbyt/sprites/Sprite/index.html
docs/templates/base.html
docs/templates/class.html
docs/templates/module.html
examples/COPYING
examples/basic1.py
examples/basic2.py
examples/basic3.py
examples/basic4.py
examples/basic4_pyglet.py
examples/bezier.py
examples/car.png
examples/carshadow.png
examples/collision.py
examples/driving.py
examples/extend_modes.py
examples/interpolation.py
examples/lotsofsprites.py
examples/pygame_font.py
examples/pyglet_font.py
examples/pymunk_integration.py
examples/rounded_square.png
examples/star.png
examples/star2.png
rabbyt/__init__.py
rabbyt/anim_sys.c
rabbyt/anim_sys.h
rabbyt/anims.py
rabbyt/include_gl.h
rabbyt/include_math.h
rabbyt/rabbyt._anims.c
rabbyt/rabbyt._anims.pxd
rabbyt/rabbyt._anims.pyx
rabbyt/rabbyt._rabbyt.c
rabbyt/rabbyt._rabbyt.pyx
rabbyt/rabbyt._sprites.c
rabbyt/rabbyt._sprites.pxd
rabbyt/rabbyt._sprites.pyx
rabbyt/rabbyt.collisions.c
rabbyt/rabbyt.collisions.pyx
rabbyt/rabbyt.primitives.c
rabbyt/rabbyt.primitives.pxd
rabbyt/rabbyt.primitives.pyx
rabbyt/sprites.py
tests/anim_tests.py
tests/collisions_tests.py
tests/sprite_tests.py
tests/test_quad.py