Metadata-Version: 1.1
Name: Rabbyt
Version: 0.8.3
Summary: A fast 2D sprite engine using OpenGL
Home-page: http://matthewmarshall.org/projects/rabbyt/
Author: Matthew Marshall
Author-email: matthew@matthewmarshall.org
License: MIT
Platform: UNKNOWN
Classifier: Development Status :: 4 - Beta
Classifier: Intended Audience :: Developers
Classifier: License :: OSI Approved :: MIT License
Classifier: Programming Language :: Python
Classifier: Topic :: Multimedia :: Graphics
Classifier: Topic :: Software Development :: Libraries :: Python Modules
